dotenver-1.3.0.dist-info/METADATA
dotenver-1.3.0.dist-info/WHEEL
dotenver-1.3.0.dist-info/entry_points.txt
dotenver-1.3.0.dist-info/licenses/LICENSE
dotenver/__init__.py
dotenver/cli.py
dotenver/dotenver.py
dotenver-1.3.0.dist-info/RECORD
