Metadata-Version: 2.1
Name: dotenver
Version: 1.3.0
Summary: Automatically generate .env files from .env.example template files
Keywords: dotenv template
Author-Email: Federico Jaramillo Martínez <federicojaramillom@gmail.com>
License: BSD-3-Clause
Classifier: Development Status :: 5 - Production/Stable
Classifier: Intended Audience :: Developers
Classifier: Natural Language :: English
Project-URL: Repository, https://github.com/jmfederico/dotenver
Requires-Python: <4.0,>=3.7
Requires-Dist: jinja2
Requires-Dist: faker
Requires-Dist: colorama
